tests
mtj
