Metadata-Version: 1.1
Name: mtj.f3u1
Version: 0.2
Summary: Factories and Functions for Fiddling with Units
Home-page: https://github.com/metatoaster/mtj.f3u1
Author: Tommy Yu
Author-email: y@metatoaster.com
License: GPL
Platform: UNKNOWN
Classifier: Programming Language :: Python
Classifier: Topic :: Software Development :: Libraries :: Python Modules
